{
  "_class": "group",
  "booleanOperation": -1,
  "do_objectID": "27A785E3-1073-4E92-8735-24AF5492E9EF",
  "exportOptions": {
    "_class": "exportOptions",
    "exportFormats": [
    ],
    "includedLayerIds": [
    ],
    "layerOptions": 0,
    "shouldTrim": false
  },
  "frame": {
    "_class": "rect",
    "constrainProportions": false,
    "height": 56,
    "width": 68,
    "x": 1012,
    "y": 0
  },
  "hasClickThrough": false,
  "isFixedToViewport": false,
  "isFlippedHorizontal": false,
  "isFlippedVertical": false,
  "isLocked": false,
  "isVisible": true,
  "layerListExpandedType": 0,
  "layers": [
    {
      "class": "group",
      "id": "C36C699B-A933-4915-B25A-EE28A11FFF36"
    },
    {
      "class": "text",
      "id": "FAB25C3E-82B5-4A4A-A9EC-562AC23D3DAF"
    },
    {
      "class": "group",
      "id": "765ED5D2-478C-4F2E-B8FA-38CF4BFEE15B"
    }
  ],
  "name": "pilot / platform-nav-item",
  "nameIsFixed": false,
  "resizingConstraint": 63,
  "resizingType": 0,
  "rotation": 0,
  "shouldBreakMaskChain": false,
  "style": {
    "_class": "style",
    "endMarkerType": 0,
    "miterLimit": 10,
    "startMarkerType": 0,
    "windingRule": 1
  }
}